Metadata-Version: 2.4
Name: my_package_lorenzouriel
Version: 0.2.0
Author: Lorenzo Uriel
Dynamic: author
Dynamic: description
Dynamic: description-content-type
